{"cameraMode":{"drawMode":0,"name":"Shaded","section":"Shading Mode"},"sceneLighting":true,"audioPlay":false,"sceneViewState":{"showFog":true,"showMaterialUpdate":false,"showSkybox":true,"showFlares":true,"showImageEffects":true,"showParticleSystems":true,"showVisualEffectGraphs":true,"m_FxEnabled":true},"in2DMode":false,"pivot":{"x":-30.073719024658204,"y":1.4317797422409058,"z":34.67900848388672},"rotation":{"x":-0.07575444132089615,"y":0.5808249115943909,"z":-0.054264046251773837,"w":-0.80876225233078},"size":10.920249938964844,"orthographic":false}